app/__init__.py
app/admin.py
app/apps.py
app/models.py
app/serializers.py
app/tests.py
app/urls.py
app/views.py
app/migrations/0001_initial.py
app/migrations/__init__.py
app/migrations/__pycache__/0001_initial.cpython-311.pyc
app/migrations/__pycache__/__init__.cpython-311.pyc
blog/__init__.py
blog/asgi.py
blog/settings.py
blog/urls.py
blog/wsgi.py
my_blog_app-0.1.1.dist-info/METADATA
my_blog_app-0.1.1.dist-info/WHEEL
my_blog_app-0.1.1.dist-info/top_level.txt
my_blog_app-0.1.1.dist-info/RECORD
